neural_models_pt/__init__.py
neural_models_pt/attentions.py
neural_models_pt/helper_layers.py
neural_models_pt/special_embedding.py
neural_models_pt/transformer.py
neural_models_tf/__init__.py
neural_models_tf/attentions.py
neural_models_tf/helper_layers.py
neural_models_tf/special_embedding.py
neural_models_tf/transformer.py
anthe_official-1.0.1.dist-info/METADATA
anthe_official-1.0.1.dist-info/WHEEL
anthe_official-1.0.1.dist-info/top_level.txt
anthe_official-1.0.1.dist-info/RECORD
