Metadata-Version: 2.1
Name: anthe-official
Version: 1.0.1
Summary: Anthe improves performance of Transformers with less parameters.
Author: Luca Herranz-Celotti, Ermal Rrapaj
Author-email: luca.herrtti@gmail.com
License: Apache License
Classifier: Development Status :: 3 - Alpha
Classifier: Programming Language :: Python :: 3 :: Only
Classifier: License :: OSI Approved :: MIT License
Classifier: Operating System :: OS Independent
Requires-Dist: h5py (>=3.1.0)
Requires-Dist: numpy (>=1.23.3)
Requires-Dist: pandas (>=1.4.0)
Requires-Dist: scikit-learn (>=1.1.3)
Requires-Dist: sentencepiece (>=0.1.97)
Requires-Dist: tensorflow (>=2.10.0)
Requires-Dist: tqdm (>=4.64.0)
Requires-Dist: pyaromatics (==0.0.2)
